{
	"cmake" : 
	{
		"generator" : 
		{
			"multiConfig" : false,
			"name" : "Ninja"
		},
		"paths" : 
		{
			"cmake" : "G:/SDK/visual studio/Common7/IDE/CommonExtensions/Microsoft/CMake/CMake/bin/cmake.exe",
			"cpack" : "G:/SDK/visual studio/Common7/IDE/CommonExtensions/Microsoft/CMake/CMake/bin/cpack.exe",
			"ctest" : "G:/SDK/visual studio/Common7/IDE/CommonExtensions/Microsoft/CMake/CMake/bin/ctest.exe",
			"root" : "G:/SDK/visual studio/Common7/IDE/CommonExtensions/Microsoft/CMake/CMake/share/cmake-3.31"
		},
		"version" : 
		{
			"isDirty" : false,
			"major" : 3,
			"minor" : 31,
			"patch" : 6,
			"string" : "3.31.6-msvc6",
			"suffix" : "msvc6"
		}
	},
	"objects" : 
	[
		{
			"jsonFile" : "codemodel-v2-5d1f0b2c714e62628569.json",
			"kind" : "codemodel",
			"version" : 
			{
				"major" : 2,
				"minor" : 8
			}
		},
		{
			"jsonFile" : "cache-v2-f573799304667528f863.json",
			"kind" : "cache",
			"version" : 
			{
				"major" : 2,
				"minor" : 0
			}
		},
		{
			"jsonFile" : "cmakeFiles-v1-f80c30d85dfe19f9ab3c.json",
			"kind" : "cmakeFiles",
			"version" : 
			{
				"major" : 1,
				"minor" : 1
			}
		},
		{
			"jsonFile" : "toolchains-v1-4b155c3b2365edd0fd5a.json",
			"kind" : "toolchains",
			"version" : 
			{
				"major" : 1,
				"minor" : 0
			}
		}
	],
	"reply" : 
	{
		"client-MicrosoftVS" : 
		{
			"query.json" : 
			{
				"requests" : 
				[
					{
						"kind" : "cache",
						"version" : 2
					},
					{
						"kind" : "cmakeFiles",
						"version" : 1
					},
					{
						"kind" : "codemodel",
						"version" : 2
					},
					{
						"kind" : "toolchains",
						"version" : 1
					}
				],
				"responses" : 
				[
					{
						"jsonFile" : "cache-v2-f573799304667528f863.json",
						"kind" : "cache",
						"version" : 
						{
							"major" : 2,
							"minor" : 0
						}
					},
					{
						"jsonFile" : "cmakeFiles-v1-f80c30d85dfe19f9ab3c.json",
						"kind" : "cmakeFiles",
						"version" : 
						{
							"major" : 1,
							"minor" : 1
						}
					},
					{
						"jsonFile" : "codemodel-v2-5d1f0b2c714e62628569.json",
						"kind" : "codemodel",
						"version" : 
						{
							"major" : 2,
							"minor" : 8
						}
					},
					{
						"jsonFile" : "toolchains-v1-4b155c3b2365edd0fd5a.json",
						"kind" : "toolchains",
						"version" : 
						{
							"major" : 1,
							"minor" : 0
						}
					}
				]
			}
		}
	}
}
